{
  "collectionName": "components_shared_testimonials",
  "info": {
    "displayName": "TestimonialItem",
    "icon": "asterisk",
    "description": ""
  },
  "options": {},
  "attributes": {
    "title": {
      "type": "string",
      "required": true
    },
    "rating": {
      "type": "enumeration",
      "enum": [
        "one",
        "two",
        "three",
        "four",
        "five"
      ],
      "required": true
    },
    "text": {
      "type": "text",
      "required": true
    }
  }
}
